coinconverter/__init__.py
coinconverter/coinconverter.py
coinconverter-0.0.4.dist-info/METADATA
coinconverter-0.0.4.dist-info/WHEEL
coinconverter-0.0.4.dist-info/top_level.txt
coinconverter-0.0.4.dist-info/RECORD
